{
  "id": "500d1a9e-1515-4f70-876f-b4d42841161b",
  "slug": "book-harry-potter",
  "subCategoryId": "book-fiction",
  "name": "哈利·波特与魔法石",
  "summary": "奇幻文学现象。",
  "description": "哈利·波特与魔法石：奇幻文学现象。\n\n**概述**：哈利·波特与魔法石在本分类中作为代表性条目，用于科普与视觉参考。\n\n**特征**：奇幻文学现象。\n\n**延伸**：可与同子类条目对照，理解设计/自然/文化史脉络。\n\n**标签**：—",
  "tags": [],
  "specs": {},
  "media": {
    "provider": "pixabay",
    "query": "open books reading library desk",
    "category": "all",
    "matchTags": [],
    "requiredTags": [],
    "minMatchScore": 0,
    "imageCount": 5
  }
}
