{
  "id": "052e7953-0363-4e6c-993c-6265b72fb7e8",
  "slug": "ui-material-design-3",
  "subCategoryId": "ui-mobile",
  "name": "Material Design 3",
  "summary": "Google 2021 年推出的跨平台设计系统，强调动态配色、圆角与无障碍组件。",
  "description": "Material Design 3（M3）由 Google 在 Google I/O 2021 发布，用于 Android 12+、Flutter、Web（Material Web）等。核心概念包括：Material You 动态取色（从壁纸生成主题色）、更大圆角、强调排版层级与状态层。\n\n组件覆盖 Button、FAB、Navigation、Card、Dialog 等；提供 Figma 设计套件与开发者文档。与 Material Design 2 相比更个性化、更少「纸墨」隐喻，强化情感化表达。\n\n**相关**：与 Apple Human Interface Guidelines、Microsoft Fluent 并列主流移动端规范；Jetpack Compose 为官方 Android 实现路径。",
  "tags": [
    "Google",
    "Android",
    "设计系统",
    "Material You"
  ],
  "specs": {
    "分类": "移动端规范",
    "发布方": "Google",
    "首发": "2021",
    "平台": "Android / Flutter / Web",
    "特点": "动态配色、大圆角",
    "组件": "M3 Design Kit",
    "前身": "Material Design 2"
  },
  "media": {
    "provider": "pixabay",
    "query": "material design mobile ui",
    "matchTags": [
      "material",
      "ui"
    ]
  }
}
