{
  "id": "51c857a7-7fc1-48b0-8ffb-32bccb740587",
  "slug": "industrial-muuto-beam-lamp",
  "subCategoryId": "id-furniture",
  "name": "Muuto Beam 灯具",
  "summary": "北欧极简金属灯臂，丹麦品牌。",
  "description": "Muuto Beam 灯具为Muuto灯具代表产品，2010s 起进入家庭场景。家居工业设计关注日常使用频率、清洁便利与空间融合。\n\n经典单品常成为租屋与样板间标配，二手市场保值反映设计持久魅力。\n\n**使用场景**：灯具，耐用性，清洁与收纳\n\n**相关**：与北欧家装、厨房开放动线趋势协同",
  "tags": [
    "家居",
    "Muuto",
    "灯具",
    "设计"
  ],
  "specs": {
    "分类": "家居产品设计",
    "品牌": "Muuto",
    "类型": "灯具",
    "时期": "2010s",
    "场景": "家庭",
    "特点": "功能与美学"
  },
  "media": {
    "provider": "pixabay",
    "query": "Muuto Beam product design",
    "matchTags": [
      "muuto"
    ],
    "minMatchScore": 1,
    "imageCount": 5,
    "category": "all",
    "requiredTags": []
  }
}
