{
  "id": "c0ea4564-9f8a-4775-b7a3-01156bb55e24",
  "slug": "game-minecraft",
  "subCategoryId": "game-indie",
  "name": "我的世界",
  "summary": "方块沙盒建造。",
  "description": "我的世界：方块沙盒建造。\n\n**概述**：我的世界在本分类中作为代表性条目，用于科普与视觉参考。\n\n**特征**：方块沙盒建造。\n\n**延伸**：可与同子类条目对照，理解设计/自然/文化史脉络。\n\n**标签**：—",
  "tags": [],
  "specs": {},
  "media": {
    "provider": "pixabay",
    "query": "pixel art indie game screenshot",
    "category": "all",
    "matchTags": [],
    "requiredTags": [],
    "minMatchScore": 0,
    "imageCount": 6
  }
}
