{
  "id": "0629a9f5-4826-490d-89b7-1cdce2dc56db",
  "slug": "architecture-arch-parthenon",
  "subCategoryId": "arch-classical",
  "name": "帕特农神庙",
  "summary": "帕特农神庙，是 雅典卫城 最重要的主体建筑，又译“巴特农神庙”。",
  "tags": [
    "希腊雅典卫城的古城堡中心",
    "Parthenon Temple",
    "帕特农神庙"
  ],
  "specs": {
    "中文名": "帕特农神庙",
    "外文名": "Parthenon Temple",
    "地理位置": "希腊雅典卫城的古城堡中心",
    "所处时代": "公元前447年",
    "占地面积": "2137 m²"
  },
  "media": {
    "provider": "pixabay",
    "query": "landmark architecture",
    "category": "all",
    "matchTags": [],
    "requiredTags": [],
    "minMatchScore": 2,
    "imageCount": 5
  },
  "contentFile": "library/architecture/architecture-arch-parthenon/content.md"
}