{
  "id": "f8e197e2-4861-49e6-aaa0-784169f913e3",
  "slug": "hero-homelander",
  "subCategoryId": "hero-indie",
  "name": "祖国人 Homelander",
  "summary": "《黑袍纠察队》Vought 招牌英雄，表面正义实则自恋残暴。",
  "tags": [
    "讽刺",
    "Vought",
    "反派",
    "黑袍纠察队"
  ],
  "specs": {
    "作品": "黑袍纠察队",
    "能力": "飞行、激光眼、超级力量",
    "公司": "沃特",
    "类型": "反英雄反派"
  },
  "media": {
    "provider": "pixabay",
    "query": "Homelander action figure toy collectible",
    "matchTags": [
      "黑袍纠察队",
      "vought",
      "homelander"
    ],
    "minMatchScore": 2,
    "imageCount": 6,
    "category": "all",
    "requiredTags": []
  },
  "contentFile": "illustrated-handbook/superhero/hero-homelander/content.md"
}
