{
  "id": "5260a79c-897a-4ba9-8118-c4becbc9c378",
  "slug": "motorcycle-moto-bmw-s1000rr",
  "subCategoryId": "moto-sport",
  "name": "BMW S 1000 RR",
  "summary": "德系仿赛。",
  "tags": [
    "仿赛"
  ],
  "specs": {},
  "media": {
    "provider": "pixabay",
    "query": "BMW S 1000 RR motorcycle",
    "category": "all",
    "matchTags": [
      "bmw"
    ],
    "requiredTags": [],
    "minMatchScore": 1,
    "imageCount": 6
  },
  "contentFile": "library/motorcycle/motorcycle-moto-bmw-s1000rr/content.md"
}
