{
  "id": "94b0e6d8-846f-4ab4-af44-b319b2ea2bf7",
  "slug": "hero-nightwing-dc",
  "subCategoryId": "hero-dc",
  "name": "夜翼 Nightwing",
  "summary": "迪克·格雷森脱离罗宾身份后的独立英雄，布鲁德海文守护者。",
  "description": "夜翼 Nightwing：迪克·格雷森脱离罗宾身份后的独立英雄，布鲁德海文守护者。\n\n**概述**：夜翼 Nightwing（Nightwing）在本分类中作为代表性条目，用于科普与视觉参考。\n\n**特征**：迪克·格雷森脱离罗宾身份后的独立英雄，布鲁德海文守护者。\n\n**延伸**：可与同子类条目对照，理解设计/自然/文化史脉络。\n\n**标签**：DC、夜翼、迪克、前罗宾\n\n**规格参数**\n\n**宇宙**：DC 漫画\n**首次登场**：1984（名号）\n**本名**：迪克·格雷森\n**前身份**：罗宾\n**城市**：布鲁德海文\n**导师**：蝙蝠侠",
  "tags": [
    "DC",
    "夜翼",
    "迪克",
    "前罗宾"
  ],
  "specs": {
    "宇宙": "DC 漫画",
    "首次登场": "1984（名号）",
    "本名": "迪克·格雷森",
    "前身份": "罗宾",
    "城市": "布鲁德海文",
    "导师": "蝙蝠侠"
  },
  "media": {
    "provider": "pixabay",
    "query": "Nightwing action figure toy collectible",
    "matchTags": [
      "前罗宾",
      "nightwing"
    ],
    "minMatchScore": 0,
    "imageCount": 6,
    "category": "all",
    "requiredTags": []
  }
}
