{
  "id": "2df3bad1-ee20-4264-96c4-1a9bebebb606",
  "slug": "supercar-mclaren-720s",
  "subCategoryId": "car-italy",
  "name": "迈凯伦 720S",
  "summary": "英国沃金双涡轮 V8 超跑，单体碳纤维 Monocage II，极致空气动力学。",
  "tags": [
    "迈凯伦",
    "英国",
    "V8",
    "碳纤维"
  ],
  "specs": {
    "分类": "英国品牌",
    "厂商": "McLaren Automotive",
    "上市": "2017",
    "发动机": "4.0L V8 双涡轮",
    "功率": "约 720 hp",
    "车身": "Monocage II 碳纤维",
    "总部": "英国沃金"
  },
  "media": {
    "provider": "pixabay",
    "query": "720S supercar",
    "matchTags": [
      "迈凯伦",
      "碳纤维"
    ],
    "minMatchScore": 1,
    "imageCount": 5,
    "category": "all",
    "requiredTags": []
  },
  "contentFile": "library/supercar/supercar-mclaren-720s/content.md"
}
