{
  "id": "3b523386-49dc-4b8e-8003-4ba4ccd6f991",
  "slug": "interior-tea-room",
  "subCategoryId": "int-modern",
  "name": "茶室",
  "summary": "榻榻米、蹲踞入口与一期一会茶道空间。",
  "description": "茶室源于日本茶道传统，强调人与自然的和室关系。材料多用竹、木、石与和纸，色调偏大地色系，减少视觉噪音以利冥想。\n\n现代都市住宅常将禅意元素局部化，如枯山水阳台或榻榻米角落。\n\n**营造要点**：茶道，自然材质，留白与秩序\n\n**相关**：与北欧极简、中式园林可对话融合",
  "tags": [
    "日式",
    "禅意",
    "茶道",
    "和室"
  ],
  "specs": {
    "分类": "日式禅意",
    "元素": "茶道",
    "空间": "和室",
    "材质": "木、竹、石、纸",
    "原则": "留白、自然",
    "场景": "茶、宿、庭"
  },
  "media": {
    "provider": "pixabay",
    "query": "茶室 interior design room",
    "matchTags": [],
    "minMatchScore": 1,
    "imageCount": 5
  }
}
